azure/mgmt/datashare/__init__.py
azure/mgmt/datashare/_configuration.py
azure/mgmt/datashare/_data_share_management_client.py
azure/mgmt/datashare/_version.py
azure/mgmt/datashare/aio/__init__.py
azure/mgmt/datashare/aio/_configuration.py
azure/mgmt/datashare/aio/_data_share_management_client.py
azure/mgmt/datashare/aio/operations/__init__.py
azure/mgmt/datashare/aio/operations/_accounts_operations.py
azure/mgmt/datashare/aio/operations/_consumer_invitations_operations.py
azure/mgmt/datashare/aio/operations/_consumer_source_data_sets_operations.py
azure/mgmt/datashare/aio/operations/_data_set_mappings_operations.py
azure/mgmt/datashare/aio/operations/_data_sets_operations.py
azure/mgmt/datashare/aio/operations/_invitations_operations.py
azure/mgmt/datashare/aio/operations/_operations.py
azure/mgmt/datashare/aio/operations/_provider_share_subscriptions_operations.py
azure/mgmt/datashare/aio/operations/_share_subscriptions_operations.py
azure/mgmt/datashare/aio/operations/_shares_operations.py
azure/mgmt/datashare/aio/operations/_synchronization_settings_operations.py
azure/mgmt/datashare/aio/operations/_triggers_operations.py
azure/mgmt/datashare/models/__init__.py
azure/mgmt/datashare/models/_data_share_management_client_enums.py
azure/mgmt/datashare/models/_models.py
azure/mgmt/datashare/models/_models_py3.py
azure/mgmt/datashare/operations/__init__.py
azure/mgmt/datashare/operations/_accounts_operations.py
azure/mgmt/datashare/operations/_consumer_invitations_operations.py
azure/mgmt/datashare/operations/_consumer_source_data_sets_operations.py
azure/mgmt/datashare/operations/_data_set_mappings_operations.py
azure/mgmt/datashare/operations/_data_sets_operations.py
azure/mgmt/datashare/operations/_invitations_operations.py
azure/mgmt/datashare/operations/_operations.py
azure/mgmt/datashare/operations/_provider_share_subscriptions_operations.py
azure/mgmt/datashare/operations/_share_subscriptions_operations.py
azure/mgmt/datashare/operations/_shares_operations.py
azure_mgmt_datashare-1.0.0.dist-info/METADATA
azure_mgmt_datashare-1.0.0.dist-info/WHEEL
azure_mgmt_datashare-1.0.0.dist-info/top_level.txt
azure_mgmt_datashare-1.0.0.dist-info/RECORD
